runviewer/__init__.py
runviewer/__main__.py
runviewer/__version__.py
runviewer/desktop-app.json
runviewer/main.ui
runviewer/runviewer.ico
runviewer/runviewer.svg
runviewer-3.2.4.dist-info/licenses/LICENSE.txt
runviewer-3.2.4.dist-info/METADATA
runviewer-3.2.4.dist-info/WHEEL
runviewer-3.2.4.dist-info/entry_points.txt
runviewer-3.2.4.dist-info/top_level.txt
runviewer-3.2.4.dist-info/RECORD
