Metadata-Version: 2.4
Name: runviewer
Version: 3.2.4
Summary: A program to view shots compiled by labscript
Author-email: The labscript suite community <labscriptsuite@googlegroups.com>
License: Copyright (c) 2014, Monash University
Project-URL: Homepage, http://labscriptsuite.org/
Project-URL: Documentation, https://docs.labscriptsuite.org/
Project-URL: Repository, https://github.com/labscript-suite/runviewer/
Project-URL: Downloads, https://github.com/labscript-suite/runviewer/releases/
Project-URL: Tracker, https://github.com/labscript-suite/runviewer/issues/
Keywords: experiment control,automation
Classifier: License :: OSI Approved :: BSD License
Classifier: Programming Language :: Python :: 3 :: Only
Requires-Python: >=3.8
License-File: LICENSE.txt
Requires-Dist: desktop-app>=0.1.2
Requires-Dist: labscript_utils>=3.1.0b1
Requires-Dist: labscript-c-extensions
Requires-Dist: pyqtgraph>=0.11.1
Requires-Dist: qtutils>=2.0.0
Requires-Dist: zprocess
Requires-Dist: numpy>=1.15
Requires-Dist: scipy
Requires-Dist: h5py
Provides-Extra: docs
Requires-Dist: PyQt5; extra == "docs"
Requires-Dist: Sphinx==8.2.3; extra == "docs"
Requires-Dist: sphinx-rtd-theme==3.0.2; extra == "docs"
Requires-Dist: myst_parser==4.0.1; extra == "docs"
Dynamic: license-file
